{
  "reply_mode": 1,
  "time_before_overtime": 0,
  "set_priority_automatically": false,
  "is_follow": 0,
  "category_2": "",
  "category_1": "1736497066245137",
  "follower_avatar": "https://s3-imfile.feishucdn.com/static-resource/v1/v2_6b5da10a-8b0f-475a-93d4-7e7bcf621c5g~?image_size=72x72&cut_type=&quality=&format=png&sticker_format=.webp",
  "follower": "Κατερίνα Σάκκουλα",
  "create_time": 1708527839,
  "deadline": 0,
  "archive_board_id": 1705151646989663,
  "replies": [
    {
      "is_hide_reply": false,
      "create_time": 1708680421,
      "auto_close_hit": 0,
      "id": 7338726119606092000,
      "reply_role": "TSC",
      "staff_id": 9295306,
      "type": 0,
      "is_questioner": false,
      "is_update": false,
      "editable": 0,
      "reply_email": "katerina.sakkoula@bytedance.com",
      "is_blocked_role": false,
      "is_final_solution": 0,
      "reply_name": "Κατερίνα Σάκκουλα",
      "reply_to_user_id": null,
      "is_hide_name": false,
      "core_user_id": "7043718772188251137",
      "name": "Κατερίνα Σάκκουλα",
      "blocked_roles": [],
      "items": [
        {
          "content": "<p>Hi Audrie,</p><p><br /></p><p>Hope you are well.</p><p><br /></p><p>The client uses the Shopify integration for both Pixel and Events API, and therefore deduplication is performed automatically for all events. There is no need to make any changes to the setup, while the client wouldn't also have the option to make any changes as this is a one-click integration managed by TikTok.</p><p><br /></p><p>You are able to validate that deduplication is correctly performed through looking at their Events Manager UI, where we can see that the majority of events appear under the 'Sever &amp; Browser' category. This means that they have been received via both methods, but through deduplication we have merged them and are only showing them once.</p><img alt=\"Screenshot 2024-02-23 at 09.22.49.png\" data-image_key=\"tos-alisg-i-6g3pebcbys-sg/a40375be8b7649cf85a71447bc6ebe8c.png\" height=\"127.511\" src=\"https://p16-athena-sign-sg.ibyteimg.com/tos-alisg-i-6g3pebcbys-sg/a40375be8b7649cf85a71447bc6ebe8c.png~tplv-6g3pebcbys-image.jpeg?lk3s=cbe26b3a&amp;x-expires=4833273684&amp;x-signature=HkKCZ687Do84l0oXwcgDCF78vao%3D\" width=\"375\"><p>Additionally, you can check the deduplication rate for each event through looking at the 'Event Health' tab, as shown below:</p><img alt=\"Screenshot 2024-02-23 at 09.26.25.png\" data-image_key=\"tos-alisg-i-6g3pebcbys-sg/87091753c24f496c98ae55ab87dfe5c9.png\" height=\"132.807\" src=\"https://p16-athena-sign-sg.ibyteimg.com/tos-alisg-i-6g3pebcbys-sg/87091753c24f496c98ae55ab87dfe5c9.png~tplv-6g3pebcbys-image.jpeg?lk3s=cbe26b3a&amp;x-expires=4833273684&amp;x-signature=Gvzj6KijFTEo2PR64tnlTkeYykU%3D\" width=\"375\"><p><br /></p><p>There are no outstanding actions for this setup, and therefore I will go ahead and close this ticket.</p><p><br /></p><p>Thanks,</p><p>Katerina</p></img></img>",
          "type": 6
        }
      ],
      "avatar": "https://s3-imfile.feishucdn.com/static-resource/v1/v2_6b5da10a-8b0f-475a-93d4-7e7bcf621c5g~?image_size=72x72&cut_type=&quality=&format=png&sticker_format=.webp",
      "context": {}
    }
  ],
  "enable_forced_order_type": 0,
  "plat_id": 1736490999244882,
  "archive_category_2_name": "",
  "pending_from_follower": false,
  "id": 1891197,
  "workflow_nodes": [],
  "board_id": 1705151646989663,
  "employee_email": "katerina.sakkoula@bytedance.com",
  "is_support_suggestion": 0,
  "title": "Mattel - Event Deduplication",
  "category_1_name": "Events API - Web",
  "auto_close_hit": 0,
  "relation_qual": [],
  "accountpass": 0,
  "priority": 1,
  "inner": 1,
  "vip_types": [],
  "is_impending_overtime": 0,
  "creater_lark_avatar": "https://s16-imfile-sg.feishucdn.com/static-resource/v1/v3_007c_928a3f73-5b28-427b-b834-9ebe37f377hu~?image_size=72x72&cut_type=&quality=&format=png&sticker_format=.webp",
  "enable_compliance_mode": false,
  "type": 0,
  "current_role": null,
  "fd_permission": 1,
  "status": 3,
  "business_data": [],
  "update_time": 1708680441,
  "owner_name": "Audrie Tan",
  "enable_auto_close_v2": 0,
  "time_after_overtime": 0,
  "swim_lane_status": 5,
  "enable_forced_order_tag": 1,
  "satisfied": 0,
  "category_2_name": "",
  "reply_name": " MPO Technical Implementation  Team",
  "is_guest": false,
  "archive_category_2": "",
  "archive_category_1_name": "Events API - Web",
  "archive_category_1": "1736497066245137",
  "allow_reopen": 0,
  "categories": [
    {
      "to_user": 1,
      "categories_id": "1736497066245137",
      "cate_1_form_id": 1736491088651314,
      "sub_cates": [
        {
          "to_user": 0,
          "categories_id": "1772385714882593",
          "value": "Lima"
        },
        {
          "to_user": 0,
          "categories_id": "1772385714882609",
          "value": "TagHero"
        },
        {
          "to_user": 0,
          "categories_id": "1772385714883585",
          "value": "Pixeron"
        },
        {
          "to_user": 0,
          "categories_id": "1772385714883601",
          "value": "Kraken Data"
        },
        {
          "to_user": 0,
          "categories_id": "1772385748400130",
          "value": "Stape"
        },
        {
          "to_user": 0,
          "categories_id": "1772385748400146",
          "value": "AccuraCast"
        },
        {
          "to_user": 0,
          "categories_id": "1772385748400162",
          "value": "DataHash"
        },
        {
          "to_user": 0,
          "categories_id": "1772385748400178",
          "value": "SignalSight"
        },
        {
          "to_user": 0,
          "categories_id": "1772385748401154",
          "value": "Tiger Pistol"
        },
        {
          "to_user": 0,
          "categories_id": "1772385748401170",
          "value": "Panomix"
        },
        {
          "to_user": 0,
          "categories_id": "1772385748401186",
          "value": "NNT"
        },
        {
          "to_user": 0,
          "categories_id": "1772385748401202",
          "value": "E-Cens"
        },
        {
          "to_user": 0,
          "categories_id": "1772548708426753",
          "value": "TSC"
        }
      ],
      "value": "Events API - Web"
    }
  ],
  "core_user_id": "6963512771926033409",
  "plat_name": "MPO Technical Implementation",
  "follower_role": "TSC",
  "remark": "",
  "show_auto_assign": false,
  "is_overtime": 0,
  "creater_lark_name": "Audrie Tan",
  "follow_employee_id": 9295306,
  "is_order_top": 0,
  "urged": 0,
  "im_chat_id": "",
  "is_delay": 0,
  "enable_forced_priority": 0,
  "pending_time": 2529243,
  "debug_permission": 1,
  "is_vip": 0,
  "items": [
    {
      "label": "Ticket Title",
      "content": "Mattel - Event Deduplication",
      "valid": true,
      "item_id": 1736491088652290,
      "type": 14,
      "option_meaning": -1
    },
    {
      "label": "Is this consultation request to help your client get to Signals Optimal? ",
      "content": "Yes, my request is to get my client to Signals Optimal",
      "valid": true,
      "key": "Yes, my request is to get my client to Signals Optimal",
      "item_id": 1774551082736689,
      "type": 9,
      "option_meaning": -1
    },
    {
      "label": "As what stage is your Signals discussion with your client?",
      "content": "Post-Pitch but client has more questions",
      "valid": true,
      "key": "Post-Pitch but client has more questions",
      "item_id": 1774551082737697,
      "type": 9,
      "option_meaning": -1
    },
    {
      "label": "Is the partner using a third party platform for Web Pixel and/or Server side tagging?",
      "content": "Shopify",
      "valid": true,
      "key": "Shopify",
      "item_id": 1774551147185217,
      "type": 4,
      "option_meaning": -1
    },
    {
      "label": "Advertiser / Client Name",
      "content": "Mattel",
      "valid": true,
      "item_id": 1736491088652306,
      "type": 1,
      "option_meaning": 6
    },
    {
      "label": "Client Vertical ",
      "content": "Other",
      "valid": true,
      "key": "Other",
      "item_id": 1736491088652322,
      "type": 4,
      "option_meaning": -1
    },
    {
      "label": "GBS Account Tier",
      "content": "Enterprise",
      "valid": true,
      "key": "Enterprise",
      "item_id": 1736492036013090,
      "type": 4,
      "option_meaning": -1
    },
    {
      "label": "GBS Country / Region",
      "content": "EU-GB",
      "valid": true,
      "key": "EU",
      "item_id": 1736491882822689,
      "type": 4,
      "option_meaning": 0
    },
    {
      "label": "Your Department / Team",
      "content": "CST",
      "valid": true,
      "key": "CST",
      "item_id": 1736491882823729,
      "type": 4,
      "option_meaning": -1
    },
    {
      "label": "Ad Account ID(s)",
      "content": [
        "7244177591274356738"
      ],
      "valid": true,
      "item_id": 1736492509963313,
      "type": 18,
      "option_meaning": 4
    },
    {
      "label": "Advertiser Priority Level/Tier",
      "content": "P1",
      "valid": true,
      "key": "P1",
      "item_id": 1740206947358722,
      "type": 4,
      "option_meaning": 2
    },
    {
      "label": "Please list name & role of Account Team for this client (BPM/CSM/ADE etc.)",
      "content": "Audrie Tan",
      "valid": true,
      "item_id": 1740206947359746,
      "type": 1,
      "option_meaning": -1
    },
    {
      "label": "Business Center ID",
      "content": "",
      "valid": true,
      "item_id": 1736492509964289,
      "type": 1,
      "option_meaning": 10
    },
    {
      "label": "Pixel ID",
      "content": "CJ1926RC77U410PV93GG",
      "valid": true,
      "item_id": 1740206947359762,
      "type": 1,
      "option_meaning": -1
    },
    {
      "label": "Website URL(s)",
      "content": [
        "https://shopping.mattel.com/en-gb"
      ],
      "valid": true,
      "item_id": 1771654477299713,
      "type": 18,
      "option_meaning": -1
    },
    {
      "label": "Product for Implementation",
      "content": "Events API - Web",
      "valid": true,
      "key": "Events API - Web",
      "item_id": 1736494728349698,
      "type": 4,
      "option_meaning": -1
    },
    {
      "label": "Target Implementation Date",
      "content": "2024-02-21",
      "valid": true,
      "item_id": 1736500801975346,
      "type": 11,
      "option_meaning": -1
    },
    {
      "label": "Does your client have Developer Resources available to support the implementation?",
      "content": "Yes",
      "valid": true,
      "key": "Yes",
      "item_id": 1736494728350770,
      "type": 4,
      "option_meaning": -1
    },
    {
      "label": "Reason for request: Please briefly describe the help needed for this account.",
      "content": "Hi, my client already has Pixel and Events API implemented via Shopify integration - however, they are trying to implement Event Deduplication and can't seem to do this based on the guide that we shared: https://business-api.tiktok.com/portal/docs?id=1771100965992450\n\nIt would be easier and faster if we could get on a call with them to walk them through this - I've already tried raising an Athena ticket on this issue (#1888310) but it's not really helping to address their question.\n\nPlease let me know availability for this week - thank you!",
      "valid": true,
      "item_id": 1736494803233810,
      "type": 2,
      "option_meaning": 8
    },
    {
      "label": "Screenshot",
      "content": [
        {
          "url": "https://p16-athena-sign-sg.ibyteimg.com/tos-alisg-i-6g3pebcbys-sg/87091753c24f496c98ae55ab87dfe5c9.png~tplv-6g3pebcbys-image.jpeg?lk3s=cbe26b3a&x-expires=4833273684&x-signature=Gvzj6KijFTEo2PR64tnlTkeYykU%3D",
          "file_name": "file_20240323_16_01_24_808313",
          "file_url": "https://p16-athena-sign-sg.ibyteimg.com/tos-alisg-i-6g3pebcbys-sg/87091753c24f496c98ae55ab87dfe5c9.png~tplv-6g3pebcbys-image.jpeg?lk3s=cbe26b3a&x-expires=4833273684&x-signature=Gvzj6KijFTEo2PR64tnlTkeYykU%3D",
          "file_key": "tos-alisg-i-6g3pebcbys-sg/87091753c24f496c98ae55ab87dfe5c9.png",
          "file_type": "jpeg",
          "biz_type": 2
        },
        {
          "url": "https://p16-athena-sign-sg.ibyteimg.com/tos-alisg-i-6g3pebcbys-sg/a40375be8b7649cf85a71447bc6ebe8c.png~tplv-6g3pebcbys-image.jpeg?lk3s=cbe26b3a&x-expires=4833273684&x-signature=HkKCZ687Do84l0oXwcgDCF78vao%3D",
          "file_name": "file_20240323_16_01_24_808384",
          "file_url": "https://p16-athena-sign-sg.ibyteimg.com/tos-alisg-i-6g3pebcbys-sg/a40375be8b7649cf85a71447bc6ebe8c.png~tplv-6g3pebcbys-image.jpeg?lk3s=cbe26b3a&x-expires=4833273684&x-signature=HkKCZ687Do84l0oXwcgDCF78vao%3D",
          "file_key": "tos-alisg-i-6g3pebcbys-sg/a40375be8b7649cf85a71447bc6ebe8c.png",
          "file_type": "jpeg",
          "biz_type": 2
        }
      ],
      "valid": true,
      "item_id": 1740206947357746,
      "type": 5,
      "option_meaning": -1
    },
    {
      "label": "categorization",
      "content": {
        "category_1_name": "Events API - Web-Events API - Web"
      },
      "valid": true,
      "item_id": 0,
      "type": 3,
      "option_meaning": -1
    }
  ],
  "fs_permission": 1,
  "auto_close_time_left": null
}